jira_metrics_extract/__init__.py
jira_metrics_extract/charting.py
jira_metrics_extract/cli.py
jira_metrics_extract/config.py
jira_metrics_extract/cycletime.py
jira_metrics_extract/query.py
jira_metrics_extract-0.53.dist-info/DESCRIPTION.rst
jira_metrics_extract-0.53.dist-info/METADATA
jira_metrics_extract-0.53.dist-info/RECORD
jira_metrics_extract-0.53.dist-info/WHEEL
jira_metrics_extract-0.53.dist-info/entry_points.txt
jira_metrics_extract-0.53.dist-info/metadata.json
jira_metrics_extract-0.53.dist-info/top_level.txt
