Metadata-Version: 2.0
Name: jira-metrics-extract
Version: 0.53
Summary: Extract agile metrics data from JIRA
Home-page: https://github.com/rnwolf/jira-metrics-extract
Author: Rudiger Wolf
Author-email: rudiger.wolf@throughputfocus.com
License: MIT
Download-URL: https://github.com/rnwolf/jira-metrics-extract/archive/{0}.tar.gz".format(version),
Keywords: agile metrics jira analytics kanban cfd
Platform: UNKNOWN
Classifier: Development Status :: 3 - Alpha
Classifier: Topic :: Utilities
Classifier: Environment :: Console
Classifier: Intended Audience :: Developers
Classifier: License :: OSI Approved :: MIT License
Classifier: Operating System :: MacOS :: MacOS X
Classifier: Operating System :: Microsoft :: Windows
Classifier: Operating System :: POSIX :: Linux
Classifier: Programming Language :: Python :: 2.7
Classifier: Programming Language :: Python :: 3.5
Classifier: Topic :: Office/Business :: Scheduling
Requires-Dist: jira
Requires-Dist: PyYAML
Requires-Dist: pandas (>=0.18)
Requires-Dist: numpy
Requires-Dist: python-dateutil
Requires-Dist: dateparser (==0.6.0)
Requires-Dist: pydicti
Requires-Dist: openpyxl
Requires-Dist: future
Requires-Dist: pytz
Provides-Extra: charting
Requires-Dist: seaborn; extra == 'charting'
Requires-Dist: matplotlib; extra == 'charting'
Requires-Dist: statsmodels; extra == 'charting'
